imbalanced_spdf/__init__.py
imbalanced_spdf/ensemble.py
imbalanced_spdf/main.py
imbalanced_spdf/tree.py
imbalanced_spdf/utils.py
imbalanced_spdf-0.0.18.dist-info/LICENSE
imbalanced_spdf-0.0.18.dist-info/METADATA
imbalanced_spdf-0.0.18.dist-info/WHEEL
imbalanced_spdf-0.0.18.dist-info/top_level.txt
imbalanced_spdf-0.0.18.dist-info/RECORD
