Metadata-Version: 2.2
Name: imbalanced-spdf
Version: 0.0.18
Summary: A Python package for imbalanced learning with ensemble learning.
Author-email: "Rahul Goswami, Aindrila Garai, Payel Sadhukhan, Palash Ghosh, Tanujit Chakraborty" <yuvrajiro@gmail.com>
License: MIT License
Project-URL: Homepage, https://github.com/yuvrajiro/imbalanced-spdf
Project-URL: Documentation, https://imbalanced-spdf.readthedocs.io
Project-URL: Source Code, https://github.com/yuvrajiro/imbalanced-spdf
Project-URL: Bug Tracker, https://github.com/yuvrajiro/imbalanced-spdf/issues
Project-URL: Release Notes, https://imbalanced-spdf.readthedocs.io/en/latest/release_notes.html
Keywords: Imbalanced Data,Ensemble Learning,Surface to Volume Ratio,Computational Complexity
Classifier: License :: OSI Approved :: MIT License
Classifier: Programming Language :: Python
Classifier: Programming Language :: Python :: 3
Requires-Python: >=3.9
License-File: LICENSE
Requires-Dist: scikit-learn~=1.5.0
Requires-Dist: numpy~=1.24.0
Requires-Dist: pandas~=2.2.2
Provides-Extra: dev
Requires-Dist: black[jupyter]; extra == "dev"
Requires-Dist: build; extra == "dev"
Requires-Dist: coverage; extra == "dev"
Requires-Dist: cython>=0.29; extra == "dev"
Requires-Dist: packaging; extra == "dev"
Requires-Dist: pre-commit; extra == "dev"
Requires-Dist: pytest; extra == "dev"
Requires-Dist: ruff; extra == "dev"
Requires-Dist: setuptools-scm>=6.4; extra == "dev"
Requires-Dist: tomli; extra == "dev"
Requires-Dist: tox; extra == "dev"
Provides-Extra: docs
Requires-Dist: ipython!=8.7.0; extra == "docs"
Requires-Dist: nbsphinx>=0.9.2; extra == "docs"
Requires-Dist: docutils; extra == "docs"
Requires-Dist: setuptools-scm; extra == "docs"
Requires-Dist: sphinx~=6.2.1; extra == "docs"
Requires-Dist: pydata-sphinx-theme~=0.13.3; extra == "docs"
Requires-Dist: sphinxcontrib-spelling; extra == "docs"
Requires-Dist: sphinx-design~=0.4.1; extra == "docs"
Requires-Dist: sphinx-copybutton~=0.5.2; extra == "docs"
Provides-Extra: nbval
Requires-Dist: ipykernel; extra == "nbval"
Requires-Dist: ipython!=8.7.0; extra == "nbval"
Requires-Dist: matplotlib~=3.6.2; extra == "nbval"
Requires-Dist: nbformat; extra == "nbval"
Requires-Dist: nbval>=0.10.0; extra == "nbval"
Requires-Dist: seaborn~=0.11.2; extra == "nbval"
